<annotation>
	<folder>images</folder>
	<filename>000352.jpg</filename>
	<path>images\000352.jpg</path>
	<source>
		<database>Unknown</database>
	</source>
	<size>
		<width>4960</width>
		<height>7015</height>
		<depth>1</depth>
	</size>
	<segmented>0</segmented>
	<object>
		<name>passport_full</name>
		<pose>Unspecified</pose>
		<truncated>0</truncated>
		<difficult>0</difficult>
		<bndbox>
			<xmin>943</xmin>
			<ymin>1187</ymin>
			<xmax>3943</xmax>
			<ymax>5393</ymax>
		</bndbox>
	</object>
	<object>
		<name>passport_front</name>
		<pose>Unspecified</pose>
		<truncated>0</truncated>
		<difficult>0</difficult>
		<bndbox>
			<xmin>943</xmin>
			<ymin>3287</ymin>
			<xmax>3929</xmax>
			<ymax>5393</ymax>
		</bndbox>
	</object>
	<object>
		<name>passport_back</name>
		<pose>Unspecified</pose>
		<truncated>0</truncated>
		<difficult>0</difficult>
		<bndbox>
			<xmin>936</xmin>
			<ymin>1180</ymin>
			<xmax>3943</xmax>
			<ymax>3293</ymax>
		</bndbox>
	</object>
</annotation>